lwc_common/lwc/__init__.py
lwc_common/lwc/crawler.py
lwc_common/lwc/drivers.py
lwc_common/lwc/exceptions.py
lwc_common/wrappers/__init__.py
lwc_common/wrappers/cloud_sql.py
lwc_common/wrappers/gcs.py
lwc_common-0.4.4.dist-info/WHEEL
lwc_common-0.4.4.dist-info/METADATA
lwc_common-0.4.4.dist-info/RECORD
