Metadata-Version: 2.1
Name: lwc-common
Version: 0.4.4
Summary: 
Author: AminuIsrael
Author-email: israel.aminu@data2bots.com
Requires-Python: >=3.7,<3.10
Classifier: Programming Language :: Python :: 3
Classifier: Programming Language :: Python :: 3.7
Classifier: Programming Language :: Python :: 3.8
Classifier: Programming Language :: Python :: 3.9
Requires-Dist: SQLAlchemy (>=1.4.31,<2.0.0)
Requires-Dist: google-cloud-storage (>=2.1.0,<3.0.0)
Requires-Dist: msedge-selenium-tools (>=3.141.4,<4.0.0)
Requires-Dist: pg8000 (>=1.23.0,<2.0.0)
Requires-Dist: pybigquery (>=0.10.2,<0.11.0)
Requires-Dist: requests (>=2.27.1,<3.0.0)
